global_entry_notifier/__init__.py
global_entry_notifier/__main__.py
global_entry_notifier/constants.py
global_entry_notifier/locations.py
global_entry_notifier/notifier.py
global_entry_notifier-0.3.0.dist-info/LICENSE
global_entry_notifier-0.3.0.dist-info/METADATA
global_entry_notifier-0.3.0.dist-info/WHEEL
global_entry_notifier-0.3.0.dist-info/entry_points.txt
global_entry_notifier-0.3.0.dist-info/top_level.txt
global_entry_notifier-0.3.0.dist-info/RECORD
